LICENSE.txt
README.md
setup.cfg
setup.py
authorizenet/__init__.py
authorizenet/apicontractsv1.py
authorizenet/apicontrollers.py
authorizenet/apicontrollersbase.py
authorizenet/constants.py
authorizenet/utility.py
authorizenet.egg-info/PKG-INFO
authorizenet.egg-info/SOURCES.txt
authorizenet.egg-info/dependency_links.txt
authorizenet.egg-info/requires.txt
authorizenet.egg-info/top_level.txt
tests/testpyxb.py
tests/testsmock.py
tests/testssample.py